pyreversi/__init__.py
pyreversi/args.py
pyreversi/bot.py
pyreversi/display.py
pyreversi/game.py
pyreversi/human.py
pyreversi/plateau.py
pyreversi/rules.py
pyreversi/update.py
pyreversi-1.4.2.dist-info/LICENSE.txt
pyreversi-1.4.2.dist-info/METADATA
pyreversi-1.4.2.dist-info/WHEEL
pyreversi-1.4.2.dist-info/entry_points.txt
pyreversi-1.4.2.dist-info/top_level.txt
pyreversi-1.4.2.dist-info/RECORD
